{
    "nodes": [
        {
            "id": "n0",
            "label": "Node 0",
            "x": 0.7003129730001092,
            "y": 0.7520171289797872,
            "size": 0.5,
            "color": "#E73834"
        },
        {
            "id": "n1",
            "label": "Node 1",
            "x": 0.75000408757478,
            "y": 0.9596784592140466,
            "size": 0.5,
            "color": "#E73834"
        },
        {
            "id": "n2",
            "label": "Node 2",
            "x": 0.27767412457615137,
            "y": 0.02523689204826951,
            "size": 0.5,
            "color": "#E73834"
        },
        {
            "id": "n3",
            "label": "Node 3",
            "x": 0.9732530666515231,
            "y": 0.228807590669021,
            "size": 0.5,
            "color": "#E73834"
        },
        {
            "id": "n4",
            "label": "Node 4",
            "x": 0.23504026420414448,
            "y": 0.7876044462900609,
            "size": 0.5,
            "color": "#E73834"
        },
        {
            "id": "n5",
            "label": "Node 5",
            "x": 0.8374977023340762,
            "y": 0.7455606863368303,
            "size": 0.5,
            "color": "#E73834"
        },
        {
            "id": "n6",
            "label": "Node 6",
            "x": 0.8457686291076243,
            "y": 0.8563753333874047,
            "size": 0.5,
            "color": "#E73834"
        },
        {
            "id": "n7",
            "label": "Node 7",
            "x": 0.6668967336881906,
            "y": 0.23525545559823513,
            "size": 0.5,
            "color": "#E73834"
        },
        {
            "id": "n8",
            "label": "Node 8",
            "x": 0.8132870693225414,
            "y": 0.09810260962694883,
            "size": 0.5,
            "color": "#E73834"
        },
        {
            "id": "n9",
            "label": "Node 9",
            "x": 0.7853180470410734,
            "y": 0.9757396811619401,
            "size": 0.5,
            "color": "#E73834"
        },
        {
            "id": "n10",
            "label": "Node 10",
            "x": 0.8890311224386096,
            "y": 0.3861827841028571,
            "size": 0.5,
            "color": "#E73834"
        },
        {
            "id": "n11",
            "label": "Node 11",
            "x": 0.7219532050658017,
            "y": 0.10061579896137118,
            "size": 0.5,
            "color": "#E73834"
        },
        {
            "id": "n12",
            "label": "Node 12",
            "x": 0.4869671936612576,
            "y": 0.13365688687190413,
            "size": 0.5,
            "color": "#E73834"
        },
        {
            "id": "n13",
            "label": "Node 13",
            "x": 0.3539022069890052,
            "y": 0.7988766774069518,
            "size": 0.5,
            "color": "#E73834"
        },
        {
            "id": "n14",
            "label": "Node 14",
            "x": 0.9214779541362077,
            "y": 0.11636705556884408,
            "size": 0.5,
            "color": "#E73834"
        },
        {
            "id": "n15",
            "label": "Node 15",
            "x": 0.5676341173239052,
            "y": 0.2797630976419896,
            "size": 0.5,
            "color": "#E73834"
        },
        {
            "id": "n16",
            "label": "Node 16",
            "x": 0.11478669568896294,
            "y": 0.39103250158950686,
            "size": 0.5,
            "color": "#E73834"
        },
        {
            "id": "n17",
            "label": "Node 17",
            "x": 0.17204865021631122,
            "y": 0.8479646153282374,
            "size": 0.5,
            "color": "#E73834"
        },
        {
            "id": "n18",
            "label": "Node 18",
            "x": 0.8471046481281519,
            "y": 0.1426069790031761,
            "size": 0.5,
            "color": "#E73834"
        },
        {
            "id": "n19",
            "label": "Node 19",
            "x": 0.845107567962259,
            "y": 0.4200085885822773,
            "size": 0.5,
            "color": "#E73834"
        }
    ],
    "edges": [
        {
            "id": "e0",
            "source": "n17",
            "target": "n10",
            "size": 0.5,
            "color": "#E73834"
        },
        {
            "id": "e1",
            "source": "n6",
            "target": "n0",
            "size": 0.5,
            "color": "#E73834"
        },
        {
            "id": "e2",
            "source": "n7",
            "target": "n5",
            "size": 0.5,
            "color": "#E73834"
        },
        {
            "id": "e3",
            "source": "n17",
            "target": "n18",
            "size": 0.5,
            "color": "#E73834"
        },
        {
            "id": "e4",
            "source": "n0",
            "target": "n14",
            "size": 0.5,
            "color": "#E73834"
        },
        {
            "id": "e5",
            "source": "n19",
            "target": "n2",
            "size": 0.5,
            "color": "#E73834"
        },
        {
            "id": "e6",
            "source": "n5",
            "target": "n13",
            "size": 0.5,
            "color": "#E73834"
        },
        {
            "id": "e7",
            "source": "n15",
            "target": "n0",
            "size": 0.5,
            "color": "#E73834"
        },
        {
            "id": "e8",
            "source": "n11",
            "target": "n1",
            "size": 0.5,
            "color": "#E73834"
        },
        {
            "id": "e9",
            "source": "n3",
            "target": "n10",
            "size": 0.5,
            "color": "#E73834"
        },
        {
            "id": "e10",
            "source": "n15",
            "target": "n16",
            "size": 0.5,
            "color": "#E73834"
        },
        {
            "id": "e11",
            "source": "n19",
            "target": "n12",
            "size": 0.5,
            "color": "#E73834"
        },
        {
            "id": "e12",
            "source": "n10",
            "target": "n15",
            "size": 0.5,
            "color": "#E73834"
        },
        {
            "id": "e13",
            "source": "n16",
            "target": "n17",
            "size": 0.5,
            "color": "#E73834"
        },
        {
            "id": "e14",
            "source": "n18",
            "target": "n15",
            "size": 0.5,
            "color": "#E73834"
        },
        {
            "id": "e15",
            "source": "n11",
            "target": "n9",
            "size": 0.5,
            "color": "#E73834"
        },
        {
            "id": "e16",
            "source": "n18",
            "target": "n4",
            "size": 0.5,
            "color": "#E73834"
        },
        {
            "id": "e17",
            "source": "n11",
            "target": "n10",
            "size": 0.5,
            "color": "#E73834"
        },
        {
            "id": "e18",
            "source": "n15",
            "target": "n11",
            "size": 0.5,
            "color": "#E73834"
        },
        {
            "id": "e19",
            "source": "n2",
            "target": "n14",
            "size": 0.5,
            "color": "#E73834"
        }
    ]
}